{
  "project_info": {
    "project_number": "1071891098375",
    "project_id": "shatapp-930a6",
    "storage_bucket": "shatapp-930a6.appspot.com"
  },
  "client": [
    {
      "client_info": {
        "mobilesdk_app_id": "1:1071891098375:android:ec5825d64a846fec4d73a2",
        "android_client_info": {
          "package_name": "com.example.shatapp"
        }
      },
      "oauth_client": [
        {
          "client_id": "1071891098375-a535pn23aq9gr3cpisbmnri71i8n8hl7.apps.googleusercontent.com",
          "client_type": 1,
          "android_info": {
            "package_name": "com.example.shatapp",
            "certificate_hash": "a06f2c709e48644a05f33049f8b35af63782688c"
          }
        },
        {
          "client_id": "1071891098375-ip4glfovk4h6j306vfo5aa68ocefcjge.apps.googleusercontent.com",
          "client_type": 3
        }
      ],
      "api_key": [
        {
          "current_key": "AIzaSyAW6m8UwhcF8H84zhwZQJ4oAAWGAHsdRx0"
        }
      ],
      "services": {
        "appinvite_service": {
          "other_platform_oauth_client": [
            {
              "client_id": "1071891098375-abe40u0qaa5r04qfljgtr7435p211vke.apps.googleusercontent.com",
              "client_type": 3
            },
            {
              "client_id": "1071891098375-1p1eb2s9tdf8ahbouflea6nvhsmu52es.apps.googleusercontent.com",
              "client_type": 2,
              "ios_info": {
                "bundle_id": "com.example.shatapp"
              }
            }
          ]
        }
      }
    },
    {
      "client_info": {
        "mobilesdk_app_id": "1:1071891098375:android:0eae2d01af86d8b24d73a2",
        "android_client_info": {
          "package_name": "it.venturini.shatapp"
        }
      },
      "oauth_client": [
        {
          "client_id": "1071891098375-c5njim5glk04fg2f8klctd3mlep65jdp.apps.googleusercontent.com",
          "client_type": 1,
          "android_info": {
            "package_name": "it.venturini.shatapp",
            "certificate_hash": "a06f2c709e48644a05f33049f8b35af63782688c"
          }
        },
        {
          "client_id": "1071891098375-e4ijd2eqrccbp36mf2mmqfi6odijong9.apps.googleusercontent.com",
          "client_type": 1,
          "android_info": {
            "package_name": "it.venturini.shatapp",
            "certificate_hash": "396475bf23aa16a46c3aa3dd6eab6cec8fb2c135"
          }
        },
        {
          "client_id": "1071891098375-ip4glfovk4h6j306vfo5aa68ocefcjge.apps.googleusercontent.com",
          "client_type": 3
        }
      ],
      "api_key": [
        {
          "current_key": "AIzaSyAW6m8UwhcF8H84zhwZQJ4oAAWGAHsdRx0"
        }
      ],
      "services": {
        "appinvite_service": {
          "other_platform_oauth_client": [
            {
              "client_id": "1071891098375-abe40u0qaa5r04qfljgtr7435p211vke.apps.googleusercontent.com",
              "client_type": 3
            },
            {
              "client_id": "1071891098375-1p1eb2s9tdf8ahbouflea6nvhsmu52es.apps.googleusercontent.com",
              "client_type": 2,
              "ios_info": {
                "bundle_id": "com.example.shatapp"
              }
            }
          ]
        }
      }
    }
  ],
  "configuration_version": "1"
}